LICENSE
MANIFEST.in
README.md
setup.cfg
setup.py
panwid/__init__.py
panwid/autocomplete.py
panwid/console.py
panwid/dropdown.py
panwid/highlightable.py
panwid/keymap.py
panwid/listbox.py
panwid/progressbar.py
panwid/scroll.py
panwid/sparkwidgets.py
panwid/tabview.py
panwid.egg-info/PKG-INFO
panwid.egg-info/SOURCES.txt
panwid.egg-info/dependency_links.txt
panwid.egg-info/requires.txt
panwid.egg-info/top_level.txt
panwid/datatable/__init__.py
panwid/datatable/cells.py
panwid/datatable/columns.py
panwid/datatable/common.py
panwid/datatable/dataframe.py
panwid/datatable/datatable.py
panwid/datatable/rows.py
panwid/dialog/__init__.py
test/__init__.py
test/test_datatable.py
test/test_dropdown.py