Metadata-Version: 1.2
Name: panwid
Version: 0.3.5
Summary: Useful widgets for urwid
Home-page: https://github.com/tonycpsu/panwid
Author: Tony Cebzanov
Author-email: tonycpsu@gmail.com
License: UNKNOWN
Platform: UNKNOWN
Classifier: Environment :: Console
Classifier: License :: OSI Approved :: GNU General Public License v2 (GPLv2)
Classifier: Intended Audience :: Developers
Requires-Python: >=3.6
